LICENSE
MANIFEST.in
README.md
setup.cfg
setup.py
tap_mixpanel/__init__.py
tap_mixpanel/client.py
tap_mixpanel/discover.py
tap_mixpanel/schema.py
tap_mixpanel/streams.py
tap_mixpanel/sync.py
tap_mixpanel/transform.py
tap_mixpanel.egg-info/PKG-INFO
tap_mixpanel.egg-info/SOURCES.txt
tap_mixpanel.egg-info/dependency_links.txt
tap_mixpanel.egg-info/entry_points.txt
tap_mixpanel.egg-info/requires.txt
tap_mixpanel.egg-info/top_level.txt
tap_mixpanel/schemas/annotations.json
tap_mixpanel/schemas/cohort_members.json
tap_mixpanel/schemas/cohorts.json
tap_mixpanel/schemas/engage.json
tap_mixpanel/schemas/export.json
tap_mixpanel/schemas/funnels.json
tap_mixpanel/schemas/revenue.json
tests/__init__.py
tests/tap_tester/__init__.py
tests/tap_tester/base.py
tests/tap_tester/test_mixpanel_all_fields_pagination.py
tests/tap_tester/test_mixpanel_automatic_fields.py
tests/tap_tester/test_mixpanel_bookmark.py
tests/tap_tester/test_mixpanel_discovery.py
tests/tap_tester/test_mixpanel_start_date.py
tests/unittests/__init__.py
tests/unittests/test_attribution_window.py
tests/unittests/test_client.py
tests/unittests/test_discover.py
tests/unittests/test_error_handling.py
tests/unittests/test_main.py
tests/unittests/test_request_timeout_param_value.py
tests/unittests/test_support_eu_endpoints.py
tests/unittests/test_sync.py
tests/unittests/test_transform.py
tests/unittests/test_transform_event_times.py