Metadata-Version: 1.1
Name: tap-mixpanel
Version: 1.5.0
Summary: Singer.io tap for extracting data from the mixpanel API
Home-page: UNKNOWN
Author: jeff.huth@bytecode.io
Author-email: UNKNOWN
License: UNKNOWN
Platform: UNKNOWN
Classifier: Programming Language :: Python :: 3 :: Only
